pocoyo/__init__.py
pocoyo/sqlite_database.py
pocoyo/telegram_bot.py
pocoyo/text_database.py
pocoyo-0.1.0.dist-info/METADATA
pocoyo-0.1.0.dist-info/WHEEL
pocoyo-0.1.0.dist-info/top_level.txt
pocoyo-0.1.0.dist-info/RECORD
